setup.py
UbuntuPaste.egg-info/PKG-INFO
UbuntuPaste.egg-info/SOURCES.txt
UbuntuPaste.egg-info/dependency_links.txt
UbuntuPaste.egg-info/top_level.txt
bin/up
ubuntupaste/__init__.py
ubuntupaste/config.py
ubuntupaste/parsecontent.py
ubuntupaste/ubuntupaste.py
ubuntupaste/urlrequest.py