Metadata-Version: 1.1
Name: UbuntuPaste
Version: 0.0.1
Summary: A gadget to paste file to UbuntuPaste from cli
Home-page: https://github.com/hxy9243/UbuntuPaste
Author: Kevin Hu
Author-email: hxy9243@gmail.com
License: UNKNOWN
Keywords: ubuntu pastebin
Platform: Linux
Classifier: Development Status :: 3 - Alpha
Classifier: Topic :: Utilities
Classifier: Environment :: Console
Classifier: License :: OSI Approved :: GNU Lesser General Public License v2 (LGPLv2)
